fds/__init__.py
fds/sdk/__init__.py
fds/sdk/FactSetOwnership/__init__.py
fds/sdk/FactSetOwnership/api_client.py
fds/sdk/FactSetOwnership/configuration.py
fds/sdk/FactSetOwnership/exceptions.py
fds/sdk/FactSetOwnership/model_utils.py
fds/sdk/FactSetOwnership/rest.py
fds/sdk/FactSetOwnership/api/__init__.py
fds/sdk/FactSetOwnership/api/fund_holdings_api.py
fds/sdk/FactSetOwnership/api/security_holders_api.py
fds/sdk/FactSetOwnership/api/transactions_api.py
fds/sdk/FactSetOwnership/apis/__init__.py
fds/sdk/FactSetOwnership/model/__init__.py
fds/sdk/FactSetOwnership/model/asset_type.py
fds/sdk/FactSetOwnership/model/error_response.py
fds/sdk/FactSetOwnership/model/error_response_sub_errors.py
fds/sdk/FactSetOwnership/model/frequency.py
fds/sdk/FactSetOwnership/model/fund_holding.py
fds/sdk/FactSetOwnership/model/fund_holdings_request.py
fds/sdk/FactSetOwnership/model/fund_holdings_response.py
fds/sdk/FactSetOwnership/model/holder_type.py
fds/sdk/FactSetOwnership/model/id_fund_holdings.py
fds/sdk/FactSetOwnership/model/id_holders.py
fds/sdk/FactSetOwnership/model/id_transactions.py
fds/sdk/FactSetOwnership/model/insider_transactions.py
fds/sdk/FactSetOwnership/model/insider_transactions_request.py
fds/sdk/FactSetOwnership/model/insider_transactions_request_data.py
fds/sdk/FactSetOwnership/model/insider_transactions_response.py
fds/sdk/FactSetOwnership/model/institutional_transactions.py
fds/sdk/FactSetOwnership/model/institutional_transactions_request.py
fds/sdk/FactSetOwnership/model/institutional_transactions_request_data.py
fds/sdk/FactSetOwnership/model/institutional_transactions_response.py
fds/sdk/FactSetOwnership/model/period_of_measure.py
fds/sdk/FactSetOwnership/model/row_exclusion.py
fds/sdk/FactSetOwnership/model/security_holders.py
fds/sdk/FactSetOwnership/model/security_holders_request.py
fds/sdk/FactSetOwnership/model/security_holders_response.py
fds/sdk/FactSetOwnership/model/top_n_holders.py
fds/sdk/FactSetOwnership/model/transaction_type.py
fds_sdk_factsetownership-1.2.0.dist-info/licenses/LICENSE
fds_sdk_factsetownership-1.2.0.dist-info/METADATA
fds_sdk_factsetownership-1.2.0.dist-info/WHEEL
fds_sdk_factsetownership-1.2.0.dist-info/top_level.txt
fds_sdk_factsetownership-1.2.0.dist-info/RECORD
